ChengzhenMishangwoXilieRangnvrenShuangdeMijue/README.md
ChengzhenMishangwoXilieRangnvrenShuangdeMijue/__init__.py
ChengzhenMishangwoXilieRangnvrenShuangdeMijue/__main__.py
ChengzhenMishangwoXilieRangnvrenShuangdeMijue/file.epub
ChengzhenMishangwoXilieRangnvrenShuangdeMijue/index.html
ChengzhenMishangwoXilieRangnvrenShuangdeMijue/css/__init__.py
ChengzhenMishangwoXilieRangnvrenShuangdeMijue/css/annotations.css
ChengzhenMishangwoXilieRangnvrenShuangdeMijue/css/main.css
ChengzhenMishangwoXilieRangnvrenShuangdeMijue/css/normalize.css
ChengzhenMishangwoXilieRangnvrenShuangdeMijue/css/popup.css
ChengzhenMishangwoXilieRangnvrenShuangdeMijue/font/__init__.py
ChengzhenMishangwoXilieRangnvrenShuangdeMijue/font/fontello.eot
ChengzhenMishangwoXilieRangnvrenShuangdeMijue/font/fontello.svg
ChengzhenMishangwoXilieRangnvrenShuangdeMijue/font/fontello.ttf
ChengzhenMishangwoXilieRangnvrenShuangdeMijue/font/fontello.woff
ChengzhenMishangwoXilieRangnvrenShuangdeMijue/img/__init__.py
ChengzhenMishangwoXilieRangnvrenShuangdeMijue/img/annotator-glyph-sprite.png
ChengzhenMishangwoXilieRangnvrenShuangdeMijue/img/annotator-icon-sprite.png
ChengzhenMishangwoXilieRangnvrenShuangdeMijue/img/apple-touch-icon.png
ChengzhenMishangwoXilieRangnvrenShuangdeMijue/img/cancelfullscreen.png
ChengzhenMishangwoXilieRangnvrenShuangdeMijue/img/close.png
ChengzhenMishangwoXilieRangnvrenShuangdeMijue/img/fullscreen.png
ChengzhenMishangwoXilieRangnvrenShuangdeMijue/img/loader.gif
ChengzhenMishangwoXilieRangnvrenShuangdeMijue/img/menu-icon.png
ChengzhenMishangwoXilieRangnvrenShuangdeMijue/img/save.png
ChengzhenMishangwoXilieRangnvrenShuangdeMijue/img/saved.png
ChengzhenMishangwoXilieRangnvrenShuangdeMijue/img/settings-s.png
ChengzhenMishangwoXilieRangnvrenShuangdeMijue/img/settings.png
ChengzhenMishangwoXilieRangnvrenShuangdeMijue/img/star.png
ChengzhenMishangwoXilieRangnvrenShuangdeMijue/js/__init__.py
ChengzhenMishangwoXilieRangnvrenShuangdeMijue/js/epub.js
chengzhen_mishangwo_xilie_rangnvren_shuangde_mijue-2022.10.11.0.dist-info/METADATA
chengzhen_mishangwo_xilie_rangnvren_shuangde_mijue-2022.10.11.0.dist-info/WHEEL
chengzhen_mishangwo_xilie_rangnvren_shuangde_mijue-2022.10.11.0.dist-info/entry_points.txt
chengzhen_mishangwo_xilie_rangnvren_shuangde_mijue-2022.10.11.0.dist-info/top_level.txt
chengzhen_mishangwo_xilie_rangnvren_shuangde_mijue-2022.10.11.0.dist-info/RECORD
